LICENSE
README.md
setup.py
BlockBee/BlockBeeCheckout.py
BlockBee/__init__.py
python_blockbee_checkout.egg-info/PKG-INFO
python_blockbee_checkout.egg-info/SOURCES.txt
python_blockbee_checkout.egg-info/dependency_links.txt
python_blockbee_checkout.egg-info/not-zip-safe
python_blockbee_checkout.egg-info/requires.txt
python_blockbee_checkout.egg-info/top_level.txt