Metadata-Version: 2.1
Name: python-blockbee-checkout
Version: 1.0.2
Summary: Python Library for BlockBee Checkout
Home-page: https://github.com/blockbee-io/python-blockbee-checkout
Author: BlockBee
Author-email: info@blockbee.io
License: MIT
Classifier: Programming Language :: Python
Classifier: Development Status :: 5 - Production/Stable
Classifier: Framework :: Django
Classifier: Intended Audience :: Developers
Classifier: License :: OSI Approved :: MIT License
Classifier: Natural Language :: English
Classifier: Operating System :: OS Independent
Classifier: Programming Language :: Python :: 3
License-File: LICENSE
